[
   {
       "Supplier":"Abc Inc",
       "Material":"Material11",
       "InventoryClassification":"A",
       "ShipFrom":"Ingredients",
       "ShipTo":"Helsinki",
       "MasterLeadTime":"40 Days",
       "DemonstratedLeadTime":"60 Days",
       "Confidencescore":"90%",
       "LeadTimeVariations":"High",
       "Analyticsintiatedby":"Admin",
       "ResultsUpdatedat":"22-Jun 24 at 13:24:00",
       "AVG/MedialLeadTime":"58 Days",
       "RecommondedRange": "57-60 Days",
       "ConfidenceLevel": "High Likely 70%",    
       "FinalLTtobeupdatedinS4":"58",
       "PendingForApprovalSince":"5 Days",
       "CurrentStatus":"Rejected by approver2",
       "RejectReason":"Add 2% buffer and resubmit"
    },
    {
       "Supplier":"Abc Inc",
       "Material":"Material12",
       "InventoryClassification":"A",
       "ShipFrom":"Ingredients",
       "ShipTo":"Helsinki",
       "MasterLeadTime":"45 Days",
       "DemonstratedLeadTime":"60 Days",
       "Confidencescore":"90%",
       "LeadTimeVariations":"High",
       "Analyticsintiatedby":"Admin",
       "ResultsUpdatedat":"22-Jun 24 at 13:24:00",
       "AVG/MedialLeadTime":"58 Days",
       "RecommondedRange": "57-60 Days",
       "ConfidenceLevel": "High Likely 70%",    
       "FinalLTtobeupdatedinS4":"58",
       "PendingForApprovalSince":"5 Days",
       "CurrentStatus":"Rejected by approver2",
       "RejectReason":"Add 2% buffer and resubmit"
    },
    {
       "Supplier":"Abc Inc",
       "Material":"Material13",
       "InventoryClassification":"A",
       "ShipFrom":"Ingredients",
       "ShipTo":"Helsinki",
       "MasterLeadTime":"40 Days",
       "DemonstratedLeadTime":"60 Days",
       "Confidencescore":"90%",
       "LeadTimeVariations":"High",
       "Analyticsintiatedby":"Admin",
       "ResultsUpdatedat":"22-Jun 24 at 13:24:00",
       "AVG/MedialLeadTime":"58 Days",
       "RecommondedRange": "57-60 Days",
       "ConfidenceLevel": "High Likely 70%",    
       "FinalLTtobeupdatedinS4":"58",
       "PendingForApprovalSince":"5 Days",
       "CurrentStatus":"Rejected by approver2",
       "RejectReason":"Add 2% buffer and resubmit"
    },
    {
       "Supplier":"Abc Inc",
       "Material":"Material14",
       "InventoryClassification":"A",
       "ShipFrom":"Ingredients",
       "ShipTo":"Helsinki",
       "MasterLeadTime":"40 Days",
       "DemonstratedLeadTime":"60 Days",
       "Confidencescore":"90%",
       "LeadTimeVariations":"High",
       "Analyticsintiatedby":"Admin",
       "ResultsUpdatedat":"22-Jun 24 at 13:24:00",
       "AVG/MedialLeadTime":"58 Days",
       "RecommondedRange": "57-60 Days",
       "ConfidenceLevel": "High Likely 70%",    
       "FinalLTtobeupdatedinS4":"58",
       "PendingForApprovalSince":"5 Days",
       "CurrentStatus":"Rejected by approver2",
       "RejectReason":"Add 2% buffer and resubmit"
    },
    {
       "Supplier":"Abc Inc",
       "Material":"Material15",
       "InventoryClassification":"A", 
       "ShipFrom":"Ingredients",
       "ShipTo":"Helsinki",
       "MasterLeadTime":"40 Days",
       "DemonstratedLeadTime":"60 Days",
       "Confidencescore":"90%",
       "LeadTimeVariations":"High",
       "Analyticsintiatedby":"Admin",
       "ResultsUpdatedat":"22-Jun 24 at 13:24:00",
       "AVG/MedialLeadTime":"58 Days",
       "RecommondedRange": "57-60 Days",
       "ConfidenceLevel": "High Likely 70%",    
       "FinalLTtobeupdatedinS4":"58",
       "PendingForApprovalSince":"5 Days",
       "CurrentStatus":"Rejected by approver2",
       "RejectReason":"Add 2% buffer and resubmit"
    },
    {
       "Supplier":"Abc Inc",
       "Material":"Material16",
       "InventoryClassification":"A",
       "ShipFrom":"Ingredients",
       "ShipTo":"Helsinki",
       "MasterLeadTime":"40 Days",
       "DemonstratedLeadTime":"60 Days",
       "Confidencescore":"90%",
       "LeadTimeVariations":"High",
       "Analyticsintiatedby":"Admin",
       "ResultsUpdatedat":"22-Jun 24 at 13:24:00",
       "AVG/MedialLeadTime":"58 Days",
       "RecommondedRange": "57-60 Days",
       "ConfidenceLevel": "High Likely 70%",    
       "FinalLTtobeupdatedinS4":"58",
       "PendingForApprovalSince":"5 Days",
       "CurrentStatus":"Rejected by approver2",
       "RejectReason":"Add 2% buffer and resubmit"
    },
    {
       "Supplier":"Abc Inc",
       "Material":"Material17",
       "InventoryClassification":"A",
       "ShipFrom":"Ingredients",
       "ShipTo":"Helsinki",
       "MasterLeadTime":"40 Days",
       "DemonstratedLeadTime":"60 Days",
       "Confidencescore":"90%",
       "LeadTimeVariations":"High",
       "Analyticsintiatedby":"Admin",
       "ResultsUpdatedat":"22-Jun 24 at 13:24:00",
       "AVG/MedialLeadTime":"58 Days",
       "RecommondedRange": "57-60 Days",
       "ConfidenceLevel": "High Likely 70%",    
       "FinalLTtobeupdatedinS4":"58",
       "PendingForApprovalSince":"5 Days",
       "CurrentStatus":"Rejected by approver2",
       "RejectReason":"Add 2% buffer and resubmit"
    },
    {
       "Supplier":"Abc Inc",
       "Material":"Material18",
       "InventoryClassification":"A",
       "ShipFrom":"Ingredients",
       "ShipTo":"Helsinki",
       "MasterLeadTime":"40 Days",
       "DemonstratedLeadTime":"60 Days",
       "Confidencescore":"90%",
       "LeadTimeVariations":"High",
       "Analyticsintiatedby":"Admin",
       "ResultsUpdatedat":"22-Jun 24 at 13:24:00",
       "AVG/MedialLeadTime":"58 Days",
       "RecommondedRange": "57-60 Days",
       "ConfidenceLevel": "High Likely 70%",    
       "FinalLTtobeupdatedinS4":"58",
       "PendingForApprovalSince":"5 Days",
       "CurrentStatus":"Rejected by approver2",
       "RejectReason":"Add 2% buffer and resubmit"
    },
    {
       "Supplier":"Abc Inc",
       "Material":"Material19",
       "InventoryClassification":"A",
       "ShipFrom":"Ingredients",
       "ShipTo":"Helsinki",
       "MasterLeadTime":"40 Days",
       "DemonstratedLeadTime":"60 Days",
       "Confidencescore":"90%",
       "LeadTimeVariations":"High",
       "Analyticsintiatedby":"Admin",
       "ResultsUpdatedat":"22-Jun 24 at 13:24:00",
       "AVG/MedialLeadTime":"58 Days",
       "RecommondedRange": "57-60 Days",
       "ConfidenceLevel": "High Likely 70%",    
       "FinalLTtobeupdatedinS4":"58",
       "PendingForApprovalSince":"5 Days",
       "CurrentStatus":"Rejected by approver2",
       "RejectReason":"Add 2% buffer and resubmit"
    }
]